[
    {
        "id":"b84719aa-3bd7-4d88-9f4a-213190196383",
        "name":"Пикантная говядина",
        "type":"khachapuri",
        "weight":200,
        "price":300,
        "description":"В честь этого хачапури многие называют своих детей. Говядина с овощами в сочетании с острыми соусами. Возможны разные степени остроты: от «Приятно» до «АААААА!!»"
    },
    {
        "id":"1853a865-402d-46c9-a2d6-cb2812bf20ee",
        "name":"Начос",
        "type":"snack",
        "weight":75,
        "price":150,
        "description":null
    },
    {
        "id":"0a3f9855-8cba-4ed5-8d71-3767bf30792d",
        "name":"Индейка Дорблю",
        "type":"khachapuri",
        "weight":200,
        "price":300,
        "description":"Индейка, благородно обжаренная в ещё более благородном сыре дорблю, с добавлением винограда, груши и соуса бешамель. Почти звезда Мишлен."
    },
    {
        "id":"3146f5db-6e60-4c86-8cf9-bd794aac4226",
        "name":"Классический",
        "type":"khachapuri",
        "weight":200,
        "price":250,
        "description":"Выверенная форма, знакомый формат, узнаваемый вкус. Для консервативных любителей ортодоксальности."
    },
    {
        "id":"426949d4-d814-4886-b342-d682133fa37a",
        "name":"pate",
        "type":"pate",
        "weight":200,
        "price":300,
        "description":"Вкусный паштет"
    },
    {
        "id":"6183e2c6-01f7-4809-862d-8bddd78545e2",
        "name":"Солёный арахис",
        "type":"snack",
        "weight":50,
        "price":90,
        "description":null
    },
    {
        "id":"32f989e4-5dc2-4ade-989a-7638d731c076",
        "name":"Слишком сырный",
        "type":"khachapuri",
        "weight":200,
        "price":300,
        "description":"Гауда, крем чиз, чеддер и сулугуни – лучшие друзья, которые будут таять у тебя во рту. Вы хотите сыра?! – Он есть у меня!"
    },
    {
        "id":"21e23881-07b8-4447-9c14-f66cade7a7d9",
        "name":"Карамельная курица",
        "type":"khachapuri",
        "weight":200,
        "price":290,
        "description":"Куриное филе с овощами в карамельно-кисло-сладко-бомбическом азиатском соусе. Такое ощущение, что вы в азиатском бистро, которое делали грузины, но только лучше!"
    }
]
